arcontextify/__init__.py
arcontextify/arc56_parser.py
arcontextify/cli.py
arcontextify/code_generator.py
arcontextify/templates/mcp_server.py.j2
arcontextify-0.0.3.dist-info/METADATA
arcontextify-0.0.3.dist-info/WHEEL
arcontextify-0.0.3.dist-info/entry_points.txt
arcontextify-0.0.3.dist-info/licenses/LICENSE
arcontextify-0.0.3.dist-info/RECORD
