Metadata-Version: 2.4
Name: arcontextify
Version: 0.0.3
Summary: Convert ARC-56 smart contract specifications to MCP servers
Author-email: Al O <altynbek.orumbayev@makerx.com.au>
License: MIT
License-File: LICENSE
Requires-Python: >=3.10
Requires-Dist: algokit-utils>=2.0.0
Requires-Dist: click>=8.0.0
Requires-Dist: jinja2>=3.0.0
Requires-Dist: mcp[cli]>=1.0.0
Requires-Dist: pydantic>=2.0.0
